{
  "version": 1,
  "current_phase": "24",
  "last_completed_phase": "23",
  "branch": "feat/phase27-kernel-consumers",
  "health": {
    "reality_green": false,
    "checks": {
      "DMS Alignment": false,
      "Bootstrap Consistency": true,
      "Share Sync Policy": true,
      "Backup System": true
    }
  },
  "required_surfaces": [
    "share/PM_BOOTSTRAP_STATE.json",
    "share/SSOT_SURFACE_V17.json"
  ],
  "notes": {
    "generated_at": "2025-12-07T03:46:12Z",
    "reality_green_summary": "share/REALITY_GREEN_SUMMARY.json",
    "dms_share_alignment": "OK",
    "dms_share_mismatch_count": 0
  }
}
